servicefoundry/__init__.py
servicefoundry/auto_gen/models.py
servicefoundry/builder/__init__.py
servicefoundry/builder/builders/__init__.py
servicefoundry/builder/builders/dockerfile.py
servicefoundry/builder/builders/tfy_notebook_buildpack/__init__.py
servicefoundry/builder/builders/tfy_notebook_buildpack/dockerfile_template.py
servicefoundry/builder/builders/tfy_python_buildpack/__init__.py
servicefoundry/builder/builders/tfy_python_buildpack/dockerfile_template.py
servicefoundry/builder/docker_service.py
servicefoundry/cli/__init__.py
servicefoundry/cli/__main__.py
servicefoundry/cli/cli_main.py
servicefoundry/cli/commands/__init__.py
servicefoundry/cli/commands/apply_command.py
servicefoundry/cli/commands/build_command.py
servicefoundry/cli/commands/build_logs_command.py
servicefoundry/cli/commands/create_command.py
servicefoundry/cli/commands/delete_command.py
servicefoundry/cli/commands/deploy_v2_command.py
servicefoundry/cli/commands/get_command.py
servicefoundry/cli/commands/list_command.py
servicefoundry/cli/commands/login_command.py
servicefoundry/cli/commands/logout_command.py
servicefoundry/cli/commands/logs_command.py
servicefoundry/cli/commands/patch_command.py
servicefoundry/cli/commands/redeploy_command.py
servicefoundry/cli/commands/terminate_comand.py
servicefoundry/cli/commands/trigger_command.py
servicefoundry/cli/config.py
servicefoundry/cli/console.py
servicefoundry/cli/const.py
servicefoundry/cli/display_util.py
servicefoundry/cli/util.py
servicefoundry/core/__init__.py
servicefoundry/core/login.py
servicefoundry/core/logout.py
servicefoundry/function_service/__init__.py
servicefoundry/function_service/__main__.py
servicefoundry/function_service/app.py
servicefoundry/function_service/build.py
servicefoundry/function_service/deployment_examples/class_deployment/__init__.py
servicefoundry/function_service/deployment_examples/class_deployment/deployment.py
servicefoundry/function_service/deployment_examples/class_deployment/my_module.py
servicefoundry-0.10.16.dist-info/METADATA
servicefoundry-0.10.16.dist-info/WHEEL
servicefoundry-0.10.16.dist-info/entry_points.txt
servicefoundry-0.10.16.dist-info/RECORD
