Metadata-Version: 2.1
Name: servicefoundry
Version: 0.10.16
Summary: Deploy applications and interact with the Truefoundry platform using CLI
Home-page: https://truefoundry.com
Author: Abhishek Choudhary
Author-email: abhichoudhary06@gmail.com
Requires-Python: >=3.8,<3.13
Classifier: Programming Language :: Python :: 3
Classifier: Programming Language :: Python :: 3.8
Classifier: Programming Language :: Python :: 3.9
Classifier: Programming Language :: Python :: 3.10
Classifier: Programming Language :: Python :: 3.11
Classifier: Programming Language :: Python :: 3.12
Requires-Dist: GitPython (>=3.1.41,<3.2.0)
Requires-Dist: Mako (>=1.1.6,<2.0.0)
Requires-Dist: PyJWT (>=2.0.0,<3.0.0)
Requires-Dist: PyYAML (>=6.0,<7.0)
Requires-Dist: click (>=7.0.0,<9.0.0)
Requires-Dist: docker (>=6.0.1,<8.0.0)
Requires-Dist: fastapi (>=0.56.0,<0.200.0)
Requires-Dist: filelock (>=3.8.0,<4.0.0)
Requires-Dist: gitignorefile (>=1.1.2,<2.0.0)
Requires-Dist: importlib-metadata (>=6.0.1,<8.0.0)
Requires-Dist: importlib-resources (>=5.2.0,<6.0.0)
Requires-Dist: packaging (>=20.0,<24.0)
Requires-Dist: pydantic (>=1.9.0,<3.0.0)
Requires-Dist: pygments (>=2.12.0,<3.0.0)
Requires-Dist: python-dateutil (>=2.8.2,<3.0.0)
Requires-Dist: python-socketio[client] (>=5.5.2,<6.0.0)
Requires-Dist: questionary (>=1.10.0,<2.0.0)
Requires-Dist: requests (>=2.23.0,<3.0.0)
Requires-Dist: rich (>=12.0.0,<14.0.0)
Requires-Dist: rich-click (>=1.2.1,<2.0.0)
Requires-Dist: tqdm (>=4.0.0,<5.0.0)
Requires-Dist: typing-extensions (>=3.10.0)
Requires-Dist: urllib3 (>=1.26.18,<3)
Requires-Dist: uvicorn (>=0.13.0,<0.31.0)
Requires-Dist: yq (>=3.1.0,<4.0.0)
Project-URL: Repository, https://github.com/truefoundry/servicefoundry-cli
